{"mean":{"confidence_interval":{"confidence_level":0.95,"lower_bound":33353671.32366368,"upper_bound":38564249.50554759},"point_estimate":35848391.09608583,"standard_error":1335313.574894724},"median":{"confidence_interval":{"confidence_level":0.95,"lower_bound":30984961.94642857,"upper_bound":39390342.73557693},"point_estimate":34787872.16666667,"standard_error":2233061.578647551},"median_abs_dev":{"confidence_interval":{"confidence_level":0.95,"lower_bound":1653399.8699227537,"upper_bound":9767688.350455537},"point_estimate":6823622.74432282,"standard_error":2157303.4521830264},"slope":{"confidence_interval":{"confidence_level":0.95,"lower_bound":31637371.930097677,"upper_bound":37004909.71914786},"point_estimate":34020386.24390244,"standard_error":1396171.6818935056},"std_dev":{"confidence_interval":{"confidence_level":0.95,"lower_bound":4192081.0013563843,"upper_bound":7321702.279708789},"point_estimate":6112938.272346492,"standard_error":798560.3408957438}}